energy_manager/__init__.py
energy_manager/calculator.py
energy_manager/manager.py
smart_energy_manager_lib-1.0.0.dist-info/licenses/LICENSE
tests/__init__.py
tests/test_energy_manager.py
smart_energy_manager_lib-1.0.0.dist-info/METADATA
smart_energy_manager_lib-1.0.0.dist-info/WHEEL
smart_energy_manager_lib-1.0.0.dist-info/top_level.txt
smart_energy_manager_lib-1.0.0.dist-info/RECORD
