Metadata-Version: 2.4
Name: smart_energy-manager_lib
Version: 1.0.0
Summary: A library for managing solar energy generation, consumption, and trading
Home-page: https://github.com/x24250511/energy-manager
Author: Tejas Patil
Author-email: 20104123tejaspatil@gmail.com
Project-URL: Bug Reports, https://github.com/yourusername/energy-manager/issues
Project-URL: Source, https://github.com/yourusername/energy-manager
Keywords: energy management solar renewable sustainability
Classifier: Development Status :: 4 - Beta
Classifier: Intended Audience :: Developers
Classifier: Topic :: Software Development :: Libraries :: Python Modules
Classifier: Topic :: Scientific/Engineering
Classifier: License :: OSI Approved :: MIT License
Classifier: Programming Language :: Python :: 3
Classifier: Programming Language :: Python :: 3.8
Classifier: Programming Language :: Python :: 3.9
Classifier: Programming Language :: Python :: 3.10
Classifier: Programming Language :: Python :: 3.11
Classifier: Programming Language :: Python :: 3.12
Requires-Python: >=3.8
License-File: LICENSE
Provides-Extra: dev
Requires-Dist: pytest>=7.0; extra == "dev"
Requires-Dist: pytest-cov>=4.0; extra == "dev"
Dynamic: author
Dynamic: author-email
Dynamic: classifier
Dynamic: description
Dynamic: description-content-type
Dynamic: home-page
Dynamic: keywords
Dynamic: license-file
Dynamic: project-url
Dynamic: provides-extra
Dynamic: requires-python
Dynamic: summary
